infiniChat_schema/__init__.py
infiniChat_schema/models.py
infiniChat_schema-0.0.3.dist-info/METADATA
infiniChat_schema-0.0.3.dist-info/WHEEL
infiniChat_schema-0.0.3.dist-info/top_level.txt
infiniChat_schema-0.0.3.dist-info/RECORD
